cell/__init__.py
cell/calculation_cell.py
cell/exceptions.py
cell/test_calculation_cell.py
calculation_cells-0.1.dist-info/LICENSE
calculation_cells-0.1.dist-info/METADATA
calculation_cells-0.1.dist-info/WHEEL
calculation_cells-0.1.dist-info/top_level.txt
calculation_cells-0.1.dist-info/RECORD
